
{
    "version": "4.2.3.v202011021201",
    "created": "2020-11-21 12:17",
    "nodestats": {
        "nodes": [
            {
                "id": "org.knime.base.node.preproc.pmml.missingval.compute.MissingValueHandlerNodeFactory#Missing Value",
                "nrexecs": 28,
                "nrfails": 0,
                "exectime": 3526,
                "nrcreated": 0,
                "successor": "n/a"
            },
            {
                "id": "org.knime.base.node.preproc.partition.PartitionNodeFactory#Partitioning",
                "nrexecs": 28,
                "nrfails": 0,
                "exectime": 948,
                "nrcreated": 0,
                "successor": "org.knime.base.node.stats.outlier.handler.NumericOutliersNodeFactory#Numeric Outliers"
            },
            {
                "id": "org.knime.base.node.preproc.normalize3.Normalizer3NodeFactory#Normalizer",
                "nrexecs": 62,
                "nrfails": 0,
                "exectime": 1597,
                "nrcreated": 0,
                "successor": "org.knime.base.node.mine.treeensemble2.node.randomforest.learner.regression.RandomForestRegressionLearnerNodeFactory#Random Forest Learner (Regression)"
            },
            {
                "id": "org.knime.base.node.mine.treeensemble2.node.regressiontree.learner.RegressionTreeLearnerNodeFactory#Simple Regression Tree Learner",
                "nrexecs": 33,
                "nrfails": 0,
                "exectime": 4372,
                "nrcreated": 0,
                "successor": "n/a"
            },
            {
                "id": "org.knime.base.node.mine.treeensemble2.node.regressiontree.predictor.RegressionTreePredictorNodeFactory#Simple Regression Tree Predictor",
                "nrexecs": 33,
                "nrfails": 0,
                "exectime": 4116,
                "nrcreated": 0,
                "successor": "n/a"
            },
            {
                "id": "org.knime.base.node.mine.scorer.numeric2.NumericScorer2NodeFactory#Numeric Scorer",
                "nrexecs": 116,
                "nrfails": 0,
                "exectime": 515,
                "nrcreated": 0,
                "successor": "n/a"
            },
            {
                "id": "org.knime.base.node.mine.regression.linear2.learner.LinReg2LearnerNodeFactory2#Linear Regression Learner",
                "nrexecs": 33,
                "nrfails": 3,
                "exectime": 5583,
                "nrcreated": 0,
                "successor": "n/a"
            },
            {
                "id": "org.knime.base.node.mine.treeensemble2.node.randomforest.learner.regression.RandomForestRegressionLearnerNodeFactory#Random Forest Learner (Regression)",
                "nrexecs": 50,
                "nrfails": 0,
                "exectime": 19051,
                "nrcreated": 0,
                "successor": "org.knime.base.node.mine.treeensemble2.node.randomforest.predictor.regression.RandomForestRegressionPredictorNodeFactory#Random Forest Predictor (Regression)"
            },
            {
                "id": "org.knime.base.node.mine.regression.predict3.RegressionPredictorNodeFactory2#Regression Predictor",
                "nrexecs": 33,
                "nrfails": 0,
                "exectime": 3275,
                "nrcreated": 0,
                "successor": "n/a"
            },
            {
                "id": "org.knime.base.node.mine.treeensemble2.node.randomforest.predictor.regression.RandomForestRegressionPredictorNodeFactory#Random Forest Predictor (Regression)",
                "nrexecs": 50,
                "nrfails": 0,
                "exectime": 4698,
                "nrcreated": 0,
                "successor": "org.knime.base.node.mine.scorer.numeric2.NumericScorer2NodeFactory#Numeric Scorer"
            },
            {
                "id": "org.knime.base.node.preproc.filter.column.DataColumnSpecFilterNodeFactory#Column Filter",
                "nrexecs": 4,
                "nrfails": 0,
                "exectime": 17,
                "nrcreated": 0,
                "successor": "n/a"
            },
            {
                "id": "org.knime.base.node.preproc.columntrans2.One2ManyCol2NodeFactory#One to Many",
                "nrexecs": 1,
                "nrfails": 0,
                "exectime": 67,
                "nrcreated": 1,
                "successor": "n/a"
            },
            {
                "id": "org.knime.base.node.stats.outlier.handler.NumericOutliersNodeFactory#Numeric Outliers",
                "nrexecs": 2,
                "nrfails": 0,
                "exectime": 437,
                "nrcreated": 1,
                "successor": "org.knime.base.node.mine.treeensemble2.node.randomforest.learner.regression.RandomForestRegressionLearnerNodeFactory#Random Forest Learner (Regression)"
            },
            {
                "id": "org.knime.base.node.viz.plotter.scattermatrix.ScatterMatrixNodeFactory#Scatter Matrix (local)",
                "nrexecs": 1,
                "nrfails": 0,
                "exectime": 20,
                "nrcreated": 1,
                "successor": "n/a"
            },
            {
                "id": "org.knime.js.base.node.viz.plotter.scatterSelectionAppender.ScatterPlotNodeFactory#Scatter Plot",
                "nrexecs": 10,
                "nrfails": 0,
                "exectime": 749,
                "nrcreated": 1,
                "successor": "n/a"
            },
            {
                "id": "org.knime.base.node.preproc.filter.definition.apply.FilterApplyNodeFactory#Filter Apply",
                "nrexecs": 0,
                "nrfails": 0,
                "exectime": 0,
                "nrcreated": 1,
                "successor": "n/a"
            },
            {
                "id": "org.knime.base.node.preproc.filter.row.RowFilterNodeFactory#Row Filter",
                "nrexecs": 9,
                "nrfails": 0,
                "exectime": 129,
                "nrcreated": 1,
                "successor": "org.knime.base.node.mine.treeensemble2.node.randomforest.predictor.regression.RandomForestRegressionPredictorNodeFactory#Random Forest Predictor (Regression)"
            }
        ],
        "metaNodes": {
        },
        "wrappedNodes": {
        }
    },
    "uptime": 17427740,
    "workflowsOpened": 3,
    "remoteWorkflowsOpened": 0,
    "workflowsImported": 0,
    "workflowsExported": 0,
    "launches": 1,
    "lastApplicationID": "org.knime.product.KNIME_APPLICATION",
    "timeSinceLastStart": 17427740,
    "crashes": 0,
    "properlyShutDown": false
}